MANIFEST.in
README.rst
requirements.txt
setup.py
bin/fbm-parse
fbmexplorer/__init__.py
fbmexplorer/__main__.py
fbmexplorer/parser.py
fbmexplorer.egg-info/PKG-INFO
fbmexplorer.egg-info/SOURCES.txt
fbmexplorer.egg-info/dependency_links.txt
fbmexplorer.egg-info/not-zip-safe
fbmexplorer.egg-info/requires.txt
fbmexplorer.egg-info/top_level.txt