Metadata-Version: 1.0
Name: fbmexplorer
Version: 0.12
Summary: Parser to extract Facebook Messenger Data, and explorer it on d3.js tool.
Home-page: https://github.com/adurivault/FBMessage
Author: adurivault
Author-email: a.durivault@gmail.com
License: MIT
Keywords: facebook,chat,messenger,history,visualization,dataviz
Platform: UNKNOWN
